k8s/__init__.py
k8s/base.py
k8s/client.py
k8s/config.py
k8s/fields.py
k8s/watcher.py
k8s/models/__init__.py
k8s/models/apiextensions_v1_custom_resource_definition.py
k8s/models/autoscaler.py
k8s/models/certificate.py
k8s/models/common.py
k8s/models/configmap.py
k8s/models/cronjob.py
k8s/models/custom_resource_definition.py
k8s/models/deployment.py
k8s/models/ingress.py
k8s/models/job.py
k8s/models/namespace.py
k8s/models/networking_v1_ingress.py
k8s/models/pod.py
k8s/models/pod_disruption_budget.py
k8s/models/policy_v1_pod_disruption_budget.py
k8s/models/replication_controller.py
k8s/models/resourcequota.py
k8s/models/role.py
k8s/models/role_binding.py
k8s/models/secret.py
k8s/models/service.py
k8s/models/service_account.py
k8s/models/third_party_resource.py
k8s-0.28.0.dist-info/LICENSE
k8s-0.28.0.dist-info/METADATA
k8s-0.28.0.dist-info/WHEEL
k8s-0.28.0.dist-info/top_level.txt
k8s-0.28.0.dist-info/zip-safe
k8s-0.28.0.dist-info/RECORD
