Metadata-Version: 2.1
Name: k8s
Version: 0.28.0
Summary: Python client library for the Kubernetes API
Home-page: https://github.com/fiaas/k8s
Author: FiaaS developers
Author-email: fiaas@googlegroups.com
License: Apache License
Keywords: kubernetes fiaas
Classifier: Development Status :: 3 - Alpha
Classifier: Intended Audience :: Developers
Classifier: License :: OSI Approved :: Apache Software License
Classifier: Operating System :: OS Independent
Classifier: Programming Language :: Python
Classifier: Programming Language :: Python :: 3
Classifier: Programming Language :: Python :: 3.9
Classifier: Programming Language :: Python :: 3.10
Classifier: Programming Language :: Python :: 3.11
Classifier: Programming Language :: Python :: 3.12
Classifier: Topic :: Internet
Classifier: Topic :: Software Development :: Libraries :: Python Modules
Classifier: Topic :: System :: Clustering
Classifier: Topic :: System :: Distributed Computing
License-File: LICENSE
Requires-Dist: requests ==2.32.3
Requires-Dist: pyrfc3339 ==1.1
Requires-Dist: cachetools ==5.3.3
Provides-Extra: codacy
Requires-Dist: codacy-coverage ; extra == 'codacy'
Provides-Extra: dev
Requires-Dist: tox ==3.28.0 ; extra == 'dev'
Requires-Dist: mock ==5.1.0 ; extra == 'dev'
Requires-Dist: pytest-sugar ==1.0.0 ; extra == 'dev'
Requires-Dist: pytest-html ==4.1.1 ; extra == 'dev'
Requires-Dist: pytest-cov ==5.0.0 ; extra == 'dev'
Requires-Dist: pytest-helpers-namespace ==2021.12.29 ; extra == 'dev'
Requires-Dist: pytest ==8.1.1 ; extra == 'dev'
Requires-Dist: prospector ==1.10.3 ; extra == 'dev'
Requires-Dist: setuptools ==69.5.1 ; extra == 'dev'
Provides-Extra: docs
Requires-Dist: Sphinx >=1.6.3 ; extra == 'docs'
